convpandas/__init__.py
convpandas/__main__.py
convpandas/__version__.py
convpandas/command/__init__.py
convpandas/command/csv2xlsx.py
convpandas/command/xlsx2csv.py
convpandas/common/__init__.py
convpandas/common/cli.py
convpandas-0.3.5.dist-info/LICENSE
convpandas-0.3.5.dist-info/METADATA
convpandas-0.3.5.dist-info/WHEEL
convpandas-0.3.5.dist-info/entry_points.txt
convpandas-0.3.5.dist-info/RECORD
