Metadata-Version: 2.1
Name: convpandas
Version: 0.3.5
Summary: Convert file format with pandas
Home-page: https://github.com/kurusugawa-computer/convert-fileformat-with-pandas.git
License: MIT
Keywords: pandas,csv,xlsx,excel
Author: Kurusugawa Computer Inc.
Requires-Python: >=3.9,<4.0
Classifier: Development Status :: 4 - Beta
Classifier: Environment :: Console
Classifier: Intended Audience :: Developers
Classifier: License :: OSI Approved :: MIT License
Classifier: Operating System :: OS Independent
Classifier: Programming Language :: Python :: 3
Classifier: Programming Language :: Python :: 3.9
Classifier: Programming Language :: Python :: 3.10
Classifier: Programming Language :: Python :: 3.11
Classifier: Programming Language :: Python :: 3.12
Classifier: Topic :: Utilities
Requires-Dist: openpyxl
Requires-Dist: pandas
Project-URL: Repository, https://github.com/kurusugawa-computer/convert-fileformat-with-pandas.git
